Workbook

Sheet README
A1: HISAB — Personal Finance Tracker
A2: Template with dummy data. Replace every sample row with own data.
A4: Sheet | B4: What to do with it
A5: Loan | B5: People who owe money (or are owed). Enter Name, Amount, Given -> Remaining auto-calculates. Status dropdown: Pending / Intransit / Paid.
A6: StrategicInvestment | B6: Monthly budget plan. Left = current-month cashflow allocation vs Done status. Right = goal buckets (Trip, Health Insurance, Emergency Fund, Debt) tracked Actual vs Target per month.
A7: Personal Loan Distribution | B7: Track one big loan/credit: left = where money actually went, right = planned split. Totals + Remaining auto-calculate.
A8: Freelance Earnings | B8: Client invoices: Amount / Received / Pending. Right panels = how each payout was spent.
A9: MMM YYYY (month sheets) | B9: One sheet per month. Row 2 = carry-forward from last month, Row 3 = income, Row 6+ = daily expenses (Date / Item / Amount). Total in F5 auto-updates. Right panel = category summary.
A10: Dashboard | B10: Read-only rollup. Pulls totals from month sheets + Loan sheet.
A12: Conventions
B13: • All amounts in ₹ (change number format if other currency).
B14: • Green/red conditional shading on Amount columns: negative = credit/refund, positive = spend.
B15: • Grey cells contain formulas — do not overwrite; drag them down when adding rows.
B16: • To add a new month: right-click a month tab -> Duplicate -> rename -> clear rows 6+.

Sheet Loan
A1: Name | B1: Amount | C1: Given | D1: Remaining | E1: Status | F1: Contact Info | G1: Date Given | H1: Date Settled | I1: Notes
A2: Person A | B2: 5000 | C2: 5000 | D2: =B2-C2 | E2: Paid | F2: 9000000001 | G2: 46204 | H2: 46223 | I2: Fully settled
A3: Person B | B3: 8500 | C3: 4000 | D3: =B3-C3 | E3: Intransit | F3: 9000000002 | G3: 46212 | I3: Paying in parts
A4: Person C | B4: 3500 | C4: 2500 | D4: =B4-C4 | E4: Intransit | F4: 9000000003 | G4: 46204
A5: Person D | B5: 12000 | C5: 0 | D5: =B5-C5 | E5: Pending | F5: 9000000004 | G5: 46236 | I5: Follow up monthly
A6: Person E | B6: 1000 | C6: 1000 | D6: =B6-C6 | E6: Paid | F6: 9000000005 | G6: 46188 | H6: 46203
D7: =IF(B7="","",B7-C7)
D8: =IF(B8="","",B8-C8)
D9: =IF(B9="","",B9-C9)
D10: =IF(B10="","",B10-C10)
D11: =IF(B11="","",B11-C11)
D12: =IF(B12="","",B12-C12)
D13: =IF(B13="","",B13-C13)
D14: =IF(B14="","",B14-C14)
D15: =IF(B15="","",B15-C15)
D16: =IF(B16="","",B16-C16)
D17: =IF(B17="","",B17-C17)
D18: =IF(B18="","",B18-C18)
... D60: =IF(B60="","",B60-C60)
A62: TOTAL | B62: =SUM(B2:B60) | C62: =SUM(C2:C60) | D62: =SUM(D2:D60)

Sheet StrategicInvestment
A1: MONTHLY BUDGET PLAN | G1: GOAL BUCKETS
A2: Monthly Income | B2: 40000
G3: Trip Fund | H3: =SUM(H5:H10) | I3: =SUM(I5:I10) | K3: DEBT TRACKER
A4: Plan — Current Month | D4: Plan — From Next Quarter | G4: Month | H4: Actual | I4: Target | K4: Total Debt | L4: 25000
A5: Cashflow | B5: Amt | C5: Status | D5: Cashflow | E5: Amt | G5: July | H5: 1000 | I5: 1000 | K5: Remaining | L5: =L4-SUM(L8:L20)
A6: Rent & Food | B6: 20000 | C6: Done | D6: Rent & Food | E6: 20000 | G6: August | H6: 3000 | I6: 3000
A7: Mobile EMI | B7: 3000 | C7: Done | D7: Mobile EMI | E7: 3000 | G7: September | H7: 0 | I7: 3000 | K7: Month | L7: Repaid | M7: Planned
A8: Debt Repayment | B8: 6000 | C8: Done | D8: Emergency Fund | E8: 5000 | G8: October | H8: 0 | I8: 5000 | K8: July | L8: 14000 | M8: 14000
A9: Emergency Fund | B9: 2500 | C9: Done | D9: Health Insurance | E9: 1000 | G9: November | H9: 0 | I9: 5000 | K9: August | L9: 4200 | M9: 6000
A10: Health Insurance | B10: 1000 | C10: Pending | D10: Investment | E10: 5000 | G10: December | H10: 0 | I10: 5000 | K10: September | L10: 0 | M10: 5000
A11: Investment | B11: 2000 | C11: Pending | D11: Trip Fund | E11: 3000 | K11: October | L11: 0 | M11: 0
A12: Trip Fund | B12: 1500 | C12: Done | D12: Fun | E12: 3000 | G12: Emergency Fund | H12: =SUM(H14:H19) | I12: =SUM(I14:I19) | K12: November | L12: 0 | M12: 0
A13: Fun | B13: 1500 | C13: Done | D13: Charity | E13: 500 | G13: Month | H13: Actual | I13: Target | K13: December | L13: 0 | M13: 0
A14: Charity | B14: 500 | C14: Done | D14: Total | E14: =SUM(E6:E13) | G14: July | H14: 3000 | I14: 3000
A15: Total | B15: =SUM(B6:B14) | C15: =B2-B15 | G15: August | H15: 2500 | I15: 2500
C16: <- unallocated | G16: September | H16: 0 | I16: 2500
G17: October | H17: 0 | I17: 5000
G18: November | H18: 0 | I18: 5000
G19: December | H19: 0 | I19: 5000
G21: Health Insurance | H21: =SUM(H23:H28) | I21: =SUM(I23:I28)
G22: Month | H22: Actual | I22: Target
G23: July | H23: 0 | I23: 1000
G24: August | H24: 1000 | I24: 1000
G25: September | H25: 0 | I25: 1000
G26: October | H26: 0 | I26: 1000
G27: November | H27: 0 | I27: 1000
G28: December | H28: 0 | I28: 1000
G30: Investment | H30: =SUM(H32:H37) | I30: =SUM(I32:I37)
G31: Month | H31: Actual | I31: Target
G32: July | H32: 2000 | I32: 2000
G33: August | H33: 500 | I33: 2000
G34: September | H34: 0 | I34: 2000
G35: October | H35: 0 | I35: 5000
G36: November | H36: 0 | I36: 5000
G37: December | H37: 0 | I37: 5000

Sheet Personal Loan Distribution
A1: LOAN / CREDIT UTILISATION
A2: Left = actual spends. Right = planned split. Negative amount = money in.
A3: Loan Amount | B3: 250000 | C3: Unspent | D3: =B3-SUM(C7:C60) | F3: Planned Total | G3: 250000 | H3: Unplanned | I3: =G3-SUM(H7:H60)
A6: Date | B6: Spent On | C6: Amount | D6: Note | F6: Date | G6: Planned For | H6: Amount | I6: Note
A7: 46248 | B7: Loan processing charges | C7: 3000 | D7: One-time fee | F7: 46248 | G7: Loan processing charges | H7: 3000
A8: 46248 | B8: Investment X | C8: 15000 | F8: 46249 | G8: Vendor 1 | H8: 10000
A9: 46251 | B9: Family recharge | C9: 400 | F9: 46249 | G9: Vendor 2 | H9: 10000
A10: 46252 | B10: Vendor 1 | C10: 10000 | D10: Hardware items | F10: 46254 | G10: Family support | H10: 2000
A11: 46253 | B11: Vendor 2 | C11: 9900 | D11: Materials | F11: 46266 | G11: Buffer | H11: 5000 | I11: Keep aside
A12: 46254 | B12: Investment X returned | C12: -15000 | D12: Money back in
B62: Total Spent | C62: =SUM(C7:C60) | G62: Total Planned | H62: =SUM(H7:H60)

Sheet Freelance Earnings
A1: SIDE INCOME / CLIENT LEDGER
A3: Client | B3: Invoice Amt | C3: Received | D3: Pending | E3: Date | G3: Payout 1 — how spent | J3: Payout 2 — how spent
A4: Client Alpha | B4: 90000 | C4: 27000 | D4: =B4-C4 | E4: 46204 | G4: Pot | H4: 27000 | J4: Pot | K4: 18000
A5: Client Beta | B5: 40000 | C5: 40000 | D5: =B5-C5 | E5: 46221 | G5: Left | H5: =H4-SUM(H8:H27) | J5: Left | K5: =K4-SUM(K8:K27)
A6: Client Gamma | B6: 18000 | C6: 18000 | D6: =B6-C6 | E6: 46239
A7: Client Delta | B7: 25000 | C7: 0 | D7: =B7-C7 | E7: 46254 | G7: Spent On | H7: Amount | J7: Spent On | K7: Amount
D8: =IF(B8="","",B8-C8) | G8: Home rent | H8: 13000 | J8: Credit card bill 1 | K8: 2400
D9: =IF(B9="","",B9-C9) | G9: Trip | H9: 2000 | J9: Credit card bill 2 | K9: 2500
D10: =IF(B10="","",B10-C10) | G10: Supplements | H10: 500 | J10: Trip | K10: 2500
D11: =IF(B11="","",B11-C11) | G11: Fun | H11: 1500 | J11: Debt repayment | K11: 5200
D12: =IF(B12="","",B12-C12) | G12: Tiffin | H12: 2100 | J12: Investment | K12: 3000
D13: =IF(B13="","",B13-C13) | G13: Debt repayment | H13: 5000
D14: =IF(B14="","",B14-C14) | G14: Family | H14: 200
D15: =IF(B15="","",B15-C15)
D16: =IF(B16="","",B16-C16)
D17: =IF(B17="","",B17-C17)
D18: =IF(B18="","",B18-C18)
D19: =IF(B19="","",B19-C19)
D20: =IF(B20="","",B20-C20)
D21: =IF(B21="","",B21-C21)
D22: =IF(B22="","",B22-C22)
D23: =IF(B23="","",B23-C23)
A25: TOTAL | B25: =SUM(B4:B23) | C25: =SUM(C4:C23) | D25: =SUM(D4:D23)

Sheet April 2026
A1: 46113 | B1: Monthly Expense Log
B2: Carry forward | C2: 0 | D2: (closing balance of last month)
A3: 46117 | B3: Income this month | C3: 40000 | D3: (salary + side income)
F4: BALANCE LEFT
A5: Date | B5: Item | C5: Amount | D5: Category | E5: Note | F5: =(C2+C3)-SUM(C6:C200)
A6: 46113 | B6: Grocery (sample) | C6: 850 | D6: Food | E6: Total spent | F6: =SUM(C6:C200)
A7: 46114 | B7: Rent | C7: 20000 | D7: Rent
A8: 46115 | B8: Metro card top-up | C8: 300 | D8: Transport | H8: Category | I8: Spent | J8: % of Spend
A9: 46117 | B9: Mobile EMI | C9: 3000 | D9: Bills | H9: Food | I9: =SUMIF($D$6:$D$200,H9,$C$6:$C$200) | J9: =IF($F$6=0,0,I9/$F$6)
A10: 46119 | B10: Coffee with friend | C10: 220 | D10: Fun | H10: Rent | I10: =SUMIF($D$6:$D$200,H10,$C$6:$C$200) | J10: =IF($F$6=0,0,I10/$F$6)
A11: 46121 | B11: Medicines | C11: 480 | D11: Health | H11: Transport | I11: =SUMIF($D$6:$D$200,H11,$C$6:$C$200) | J11: =IF($F$6=0,0,I11/$F$6)
A12: 46124 | B12: Tiffin service | C12: 2100 | D12: Food | H12: Shopping | I12: =SUMIF($D$6:$D$200,H12,$C$6:$C$200) | J12: =IF($F$6=0,0,I12/$F$6)
A13: 46127 | B13: Refund received | C13: -500 | D13: Other | H13: Bills | I13: =SUMIF($D$6:$D$200,H13,$C$6:$C$200) | J13: =IF($F$6=0,0,I13/$F$6)
A14: 46130 | B14: Debt repayment | C14: 4000 | D14: Debt | H14: Health | I14: =SUMIF($D$6:$D$200,H14,$C$6:$C$200) | J14: =IF($F$6=0,0,I14/$F$6)
A15: 46137 | B15: SIP investment | C15: 2000 | D15: Savings | H15: Fun | I15: =SUMIF($D$6:$D$200,H15,$C$6:$C$200) | J15: =IF($F$6=0,0,I15/$F$6)
H16: Debt | I16: =SUMIF($D$6:$D$200,H16,$C$6:$C$200) | J16: =IF($F$6=0,0,I16/$F$6)
H17: Savings | I17: =SUMIF($D$6:$D$200,H17,$C$6:$C$200) | J17: =IF($F$6=0,0,I17/$F$6)
H18: Other | I18: =SUMIF($D$6:$D$200,H18,$C$6:$C$200) | J18: =IF($F$6=0,0,I18/$F$6)
H19: Total | I19: =SUM(I9:I18)

Sheet May 2026
A1: 46143 | B1: Monthly Expense Log
B2: Carry forward | C2: ='April 2026'!F5 | D2: (closing balance of last month)
A3: 46147 | B3: Income this month | C3: 40000 | D3: (salary + side income)
F4: BALANCE LEFT
A5: Date | B5: Item | C5: Amount | D5: Category | E5: Note | F5: =(C2+C3)-SUM(C6:C200)
A6: 46143 | B6: Grocery (sample) | C6: 850 | D6: Food | E6: Total spent | F6: =SUM(C6:C200)
A7: 46144 | B7: Rent | C7: 20000 | D7: Rent
A8: 46145 | B8: Metro card top-up | C8: 300 | D8: Transport | H8: Category | I8: Spent | J8: % of Spend
A9: 46147 | B9: Mobile EMI | C9: 3000 | D9: Bills | H9: Food | I9: =SUMIF($D$6:$D$200,H9,$C$6:$C$200) | J9: =IF($F$6=0,0,I9/$F$6)
A10: 46149 | B10: Coffee with friend | C10: 220 | D10: Fun | H10: Rent | I10: =SUMIF($D$6:$D$200,H10,$C$6:$C$200) | J10: =IF($F$6=0,0,I10/$F$6)
A11: 46151 | B11: Medicines | C11: 480 | D11: Health | H11: Transport | I11: =SUMIF($D$6:$D$200,H11,$C$6:$C$200) | J11: =IF($F$6=0,0,I11/$F$6)
A12: 46154 | B12: Tiffin service | C12: 2100 | D12: Food | H12: Shopping | I12: =SUMIF($D$6:$D$200,H12,$C$6:$C$200) | J12: =IF($F$6=0,0,I12/$F$6)
A13: 46157 | B13: Refund received | C13: -500 | D13: Other | H13: Bills | I13: =SUMIF($D$6:$D$200,H13,$C$6:$C$200) | J13: =IF($F$6=0,0,I13/$F$6)
A14: 46160 | B14: Debt repayment | C14: 4000 | D14: Debt | H14: Health | I14: =SUMIF($D$6:$D$200,H14,$C$6:$C$200) | J14: =IF($F$6=0,0,I14/$F$6)
A15: 46167 | B15: SIP investment | C15: 2000 | D15: Savings | H15: Fun | I15: =SUMIF($D$6:$D$200,H15,$C$6:$C$200) | J15: =IF($F$6=0,0,I15/$F$6)
H16: Debt | I16: =SUMIF($D$6:$D$200,H16,$C$6:$C$200) | J16: =IF($F$6=0,0,I16/$F$6)
H17: Savings | I17: =SUMIF($D$6:$D$200,H17,$C$6:$C$200) | J17: =IF($F$6=0,0,I17/$F$6)
H18: Other | I18: =SUMIF($D$6:$D$200,H18,$C$6:$C$200) | J18: =IF($F$6=0,0,I18/$F$6)
H19: Total | I19: =SUM(I9:I18)

Sheet June 2026
A1: 46174 | B1: Monthly Expense Log
B2: Carry forward | C2: ='May 2026'!F5 | D2: (closing balance of last month)
A3: 46178 | B3: Income this month | C3: 40000 | D3: (salary + side income)
F4: BALANCE LEFT
A5: Date | B5: Item | C5: Amount | D5: Category | E5: Note | F5: =(C2+C3)-SUM(C6:C200)
A6: 46174 | B6: Grocery (sample) | C6: 850 | D6: Food | E6: Total spent | F6: =SUM(C6:C200)
A7: 46175 | B7: Rent | C7: 20000 | D7: Rent
A8: 46176 | B8: Metro card top-up | C8: 300 | D8: Transport | H8: Category | I8: Spent | J8: % of Spend
A9: 46178 | B9: Mobile EMI | C9: 3000 | D9: Bills | H9: Food | I9: =SUMIF($D$6:$D$200,H9,$C$6:$C$200) | J9: =IF($F$6=0,0,I9/$F$6)
A10: 46180 | B10: Coffee with friend | C10: 220 | D10: Fun | H10: Rent | I10: =SUMIF($D$6:$D$200,H10,$C$6:$C$200) | J10: =IF($F$6=0,0,I10/$F$6)
A11: 46182 | B11: Medicines | C11: 480 | D11: Health | H11: Transport | I11: =SUMIF($D$6:$D$200,H11,$C$6:$C$200) | J11: =IF($F$6=0,0,I11/$F$6)
A12: 46185 | B12: Tiffin service | C12: 2100 | D12: Food | H12: Shopping | I12: =SUMIF($D$6:$D$200,H12,$C$6:$C$200) | J12: =IF($F$6=0,0,I12/$F$6)
A13: 46188 | B13: Refund received | C13: -500 | D13: Other | H13: Bills | I13: =SUMIF($D$6:$D$200,H13,$C$6:$C$200) | J13: =IF($F$6=0,0,I13/$F$6)
A14: 46191 | B14: Debt repayment | C14: 4000 | D14: Debt | H14: Health | I14: =SUMIF($D$6:$D$200,H14,$C$6:$C$200) | J14: =IF($F$6=0,0,I14/$F$6)
A15: 46198 | B15: SIP investment | C15: 2000 | D15: Savings | H15: Fun | I15: =SUMIF($D$6:$D$200,H15,$C$6:$C$200) | J15: =IF($F$6=0,0,I15/$F$6)
H16: Debt | I16: =SUMIF($D$6:$D$200,H16,$C$6:$C$200) | J16: =IF($F$6=0,0,I16/$F$6)
H17: Savings | I17: =SUMIF($D$6:$D$200,H17,$C$6:$C$200) | J17: =IF($F$6=0,0,I17/$F$6)
H18: Other | I18: =SUMIF($D$6:$D$200,H18,$C$6:$C$200) | J18: =IF($F$6=0,0,I18/$F$6)
H19: Total | I19: =SUM(I9:I18)

Sheet July 2026
A1: 46204 | B1: Monthly Expense Log
B2: Carry forward | C2: ='June 2026'!F5 | D2: (closing balance of last month)
A3: 46208 | B3: Income this month | C3: 40000 | D3: (salary + side income)
F4: BALANCE LEFT
A5: Date | B5: Item | C5: Amount | D5: Category | E5: Note | F5: =(C2+C3)-SUM(C6:C200)
A6: 46204 | B6: Grocery (sample) | C6: 850 | D6: Food | E6: Total spent | F6: =SUM(C6:C200)
A7: 46205 | B7: Rent | C7: 20000 | D7: Rent
A8: 46206 | B8: Metro card top-up | C8: 300 | D8: Transport | H8: Category | I8: Spent | J8: % of Spend
A9: 46208 | B9: Mobile EMI | C9: 3000 | D9: Bills | H9: Food | I9: =SUMIF($D$6:$D$200,H9,$C$6:$C$200) | J9: =IF($F$6=0,0,I9/$F$6)
A10: 46210 | B10: Coffee with friend | C10: 220 | D10: Fun | H10: Rent | I10: =SUMIF($D$6:$D$200,H10,$C$6:$C$200) | J10: =IF($F$6=0,0,I10/$F$6)
A11: 46212 | B11: Medicines | C11: 480 | D11: Health | H11: Transport | I11: =SUMIF($D$6:$D$200,H11,$C$6:$C$200) | J11: =IF($F$6=0,0,I11/$F$6)
A12: 46215 | B12: Tiffin service | C12: 2100 | D12: Food | H12: Shopping | I12: =SUMIF($D$6:$D$200,H12,$C$6:$C$200) | J12: =IF($F$6=0,0,I12/$F$6)
A13: 46218 | B13: Refund received | C13: -500 | D13: Other | H13: Bills | I13: =SUMIF($D$6:$D$200,H13,$C$6:$C$200) | J13: =IF($F$6=0,0,I13/$F$6)
A14: 46221 | B14: Debt repayment | C14: 4000 | D14: Debt | H14: Health | I14: =SUMIF($D$6:$D$200,H14,$C$6:$C$200) | J14: =IF($F$6=0,0,I14/$F$6)
A15: 46228 | B15: SIP investment | C15: 2000 | D15: Savings | H15: Fun | I15: =SUMIF($D$6:$D$200,H15,$C$6:$C$200) | J15: =IF($F$6=0,0,I15/$F$6)
H16: Debt | I16: =SUMIF($D$6:$D$200,H16,$C$6:$C$200) | J16: =IF($F$6=0,0,I16/$F$6)
H17: Savings | I17: =SUMIF($D$6:$D$200,H17,$C$6:$C$200) | J17: =IF($F$6=0,0,I17/$F$6)
H18: Other | I18: =SUMIF($D$6:$D$200,H18,$C$6:$C$200) | J18: =IF($F$6=0,0,I18/$F$6)
H19: Total | I19: =SUM(I9:I18)

Sheet August 2026
A1: 46235 | B1: Monthly Expense Log
B2: Carry forward | C2: ='July 2026'!F5 | D2: (closing balance of last month)
A3: 46239 | B3: Income this month | C3: 40000 | D3: (salary + side income)
F4: BALANCE LEFT
A5: Date | B5: Item | C5: Amount | D5: Category | E5: Note | F5: =(C2+C3)-SUM(C6:C200)
A6: 46235 | B6: Grocery (sample) | C6: 850 | D6: Food | E6: Total spent | F6: =SUM(C6:C200)
A7: 46236 | B7: Rent | C7: 20000 | D7: Rent
A8: 46237 | B8: Metro card top-up | C8: 300 | D8: Transport | H8: Category | I8: Spent | J8: % of Spend
A9: 46239 | B9: Mobile EMI | C9: 3000 | D9: Bills | H9: Food | I9: =SUMIF($D$6:$D$200,H9,$C$6:$C$200) | J9: =IF($F$6=0,0,I9/$F$6)
A10: 46241 | B10: Coffee with friend | C10: 220 | D10: Fun | H10: Rent | I10: =SUMIF($D$6:$D$200,H10,$C$6:$C$200) | J10: =IF($F$6=0,0,I10/$F$6)
A11: 46243 | B11: Medicines | C11: 480 | D11: Health | H11: Transport | I11: =SUMIF($D$6:$D$200,H11,$C$6:$C$200) | J11: =IF($F$6=0,0,I11/$F$6)
A12: 46246 | B12: Tiffin service | C12: 2100 | D12: Food | H12: Shopping | I12: =SUMIF($D$6:$D$200,H12,$C$6:$C$200) | J12: =IF($F$6=0,0,I12/$F$6)
A13: 46249 | B13: Refund received | C13: -500 | D13: Other | H13: Bills | I13: =SUMIF($D$6:$D$200,H13,$C$6:$C$200) | J13: =IF($F$6=0,0,I13/$F$6)
A14: 46252 | B14: Debt repayment | C14: 4000 | D14: Debt | H14: Health | I14: =SUMIF($D$6:$D$200,H14,$C$6:$C$200) | J14: =IF($F$6=0,0,I14/$F$6)
A15: 46259 | B15: SIP investment | C15: 2000 | D15: Savings | H15: Fun | I15: =SUMIF($D$6:$D$200,H15,$C$6:$C$200) | J15: =IF($F$6=0,0,I15/$F$6)
H16: Debt | I16: =SUMIF($D$6:$D$200,H16,$C$6:$C$200) | J16: =IF($F$6=0,0,I16/$F$6)
H17: Savings | I17: =SUMIF($D$6:$D$200,H17,$C$6:$C$200) | J17: =IF($F$6=0,0,I17/$F$6)
H18: Other | I18: =SUMIF($D$6:$D$200,H18,$C$6:$C$200) | J18: =IF($F$6=0,0,I18/$F$6)
H19: Total | I19: =SUM(I9:I18)

Sheet September 2026
A1: 46266 | B1: Monthly Expense Log
B2: Carry forward | C2: ='August 2026'!F5 | D2: (closing balance of last month)
A3: 46270 | B3: Income this month | C3: 40000 | D3: (salary + side income)
F4: BALANCE LEFT
A5: Date | B5: Item | C5: Amount | D5: Category | E5: Note | F5: =(C2+C3)-SUM(C6:C200)
E6: Total spent | F6: =SUM(C6:C200)
H8: Category | I8: Spent | J8: % of Spend
H9: Food | I9: =SUMIF($D$6:$D$200,H9,$C$6:$C$200) | J9: =IF($F$6=0,0,I9/$F$6)
H10: Rent | I10: =SUMIF($D$6:$D$200,H10,$C$6:$C$200) | J10: =IF($F$6=0,0,I10/$F$6)
H11: Transport | I11: =SUMIF($D$6:$D$200,H11,$C$6:$C$200) | J11: =IF($F$6=0,0,I11/$F$6)
H12: Shopping | I12: =SUMIF($D$6:$D$200,H12,$C$6:$C$200) | J12: =IF($F$6=0,0,I12/$F$6)
H13: Bills | I13: =SUMIF($D$6:$D$200,H13,$C$6:$C$200) | J13: =IF($F$6=0,0,I13/$F$6)
H14: Health | I14: =SUMIF($D$6:$D$200,H14,$C$6:$C$200) | J14: =IF($F$6=0,0,I14/$F$6)
H15: Fun | I15: =SUMIF($D$6:$D$200,H15,$C$6:$C$200) | J15: =IF($F$6=0,0,I15/$F$6)
H16: Debt | I16: =SUMIF($D$6:$D$200,H16,$C$6:$C$200) | J16: =IF($F$6=0,0,I16/$F$6)
H17: Savings | I17: =SUMIF($D$6:$D$200,H17,$C$6:$C$200) | J17: =IF($F$6=0,0,I17/$F$6)
H18: Other | I18: =SUMIF($D$6:$D$200,H18,$C$6:$C$200) | J18: =IF($F$6=0,0,I18/$F$6)
H19: Total | I19: =SUM(I9:I18)

Sheet Dashboard
A1: DASHBOARD
A2: All values pull from other sheets. Read-only.
A4: Month | B4: Carry Fwd | C4: Income | D4: Spent | E4: Balance Left | F4: Savings Rate
A5: April 2026 | B5: ='April 2026'!C2 | C5: ='April 2026'!C3 | D5: ='April 2026'!F6 | E5: ='April 2026'!F5 | F5: =IF(C5=0,0,(C5-D5)/C5)
A6: May 2026 | B6: ='May 2026'!C2 | C6: ='May 2026'!C3 | D6: ='May 2026'!F6 | E6: ='May 2026'!F5 | F6: =IF(C6=0,0,(C6-D6)/C6)
A7: June 2026 | B7: ='June 2026'!C2 | C7: ='June 2026'!C3 | D7: ='June 2026'!F6 | E7: ='June 2026'!F5 | F7: =IF(C7=0,0,(C7-D7)/C7)
A8: July 2026 | B8: ='July 2026'!C2 | C8: ='July 2026'!C3 | D8: ='July 2026'!F6 | E8: ='July 2026'!F5 | F8: =IF(C8=0,0,(C8-D8)/C8)
A9: August 2026 | B9: ='August 2026'!C2 | C9: ='August 2026'!C3 | D9: ='August 2026'!F6 | E9: ='August 2026'!F5 | F9: =IF(C9=0,0,(C9-D9)/C9)
A10: September 2026 | B10: ='September 2026'!C2 | C10: ='September 2026'!C3 | D10: ='September 2026'!F6 | E10: ='September 2026'!F5 | F10: =IF(C10=0,0,(C10-D10)/C10)
A11: TOTAL | C11: =SUM(C5:C10) | D11: =SUM(D5:D10)
A13: Receivables & Goals
A14: Money lent out (total) | B14: =Loan!B62
A15: Still to recover | B15: =Loan!D62
A16: Client invoices raised | B16: ='Freelance Earnings'!B25
A17: Client payments pending | B17: ='Freelance Earnings'!D25
A18: Loan amount unspent | B18: ='Personal Loan Distribution'!D3
A19: Debt remaining | B19: =StrategicInvestment!L5
